{"error": "false", "response": {"solutions": {"re_features_v3": {"detections": [{"label": "hardwood_floor"}, {"label": "high_ceiling"}]}, "re_roomtype_global_v2": {"predictions": [{"label": "living_room", "confidence": 0.9255955219268799}, {"label": "sunroom", "confidence": 0.00394676998257637}, {"label": "lobby", "confidence": 0.0026803261134773493}, {"label": "garage", "confidence": 0.0026556900702416897}, {"label": "bathroom", "confidence": 0.002164494711905718}], "top_prediction": {"label": "living_room", "confidence": 0.9255955219268799}}, "re_appliances_v2": {"detections": []}}}, "time": "2022-04-30T19:03:00.265731", "correlation_id": "f3eb7ec2-e4dd-4438-8b22-eb8548836235", "version": "2"}